{"otherData": {},"traceEvents":[{"cat":"function","dur":289217,"name":"glfwInit","ph":"X","pid":0,"tid":3967693127,"ts":167748912070},{"cat":"function","dur":187220,"name":"void __cdecl CHazel::WindowsWindow::Init(const struct CHazel::WindowProps &)","ph":"X","pid":0,"tid":3967693127,"ts":167749201504},{"cat":"function","dur":2428,"name":"void __cdecl CHazel::OpenGLContext::Init(void)","ph":"X","pid":0,"tid":3967693127,"ts":167749388835},{"cat":"function","dur":15,"name":"void __cdecl CHazel::WindowsWindow::SetVSync(bool)","ph":"X","pid":0,"tid":3967693127,"ts":167749391391},{"cat":"function","dur":481154,"name":"void __cdecl CHazel::WindowsWindow::Init(const struct CHazel::WindowProps &)","ph":"X","pid":0,"tid":3967693127,"ts":167748910304},{"cat":"function","dur":481198,"name":"__cdecl CHazel::WindowsWindow::WindowsWindow(const struct CHazel::WindowProps &)","ph":"X","pid":0,"tid":3967693127,"ts":167748910303},{"cat":"function","dur":18,"name":"void __cdecl CHazel::OpenGLRendererAPI::Init(void)","ph":"X","pid":0,"tid":3967693127,"ts":167749391574},{"cat":"function","dur":11,"name":"__cdecl CHazel::OpenGLVertexArray::OpenGLVertexArray(void)","ph":"X","pid":0,"tid":3967693127,"ts":167749391664},{"cat":"function","dur":137,"name":"__cdecl CHazel::OpenGLVertexBuffer::OpenGLVertexBuffer(unsigned int)","ph":"X","pid":0,"tid":3967693127,"ts":167749391731},{"cat":"function","dur":0,"name":"void __cdecl CHazel::OpenGLVertexBuffer::Bind(void) const","ph":"X","pid":0,"tid":3967693127,"ts":167749391972},{"cat":"function","dur":76,"name":"void __cdecl CHazel::OpenGLVertexArray::AddVertexBuffer(const class std::shared_ptr<class CHazel::VertexBuffer> &)","ph":"X","pid":0,"tid":3967693127,"ts":167749391964},{"cat":"function","dur":602,"name":"__cdecl CHazel::OpenGLIndexBuffer::OpenGLIndexBuffer(unsigned int *,unsigned int)","ph":"X","pid":0,"tid":3967693127,"ts":167749392933},{"cat":"function","dur":1,"name":"void __cdecl CHazel::OpenGLIndexBuffer::Bind(void) const","ph":"X","pid":0,"tid":3967693127,"ts":167749393652},{"cat":"function","dur":59,"name":"void __cdecl CHazel::OpenGLVertexArray::SetIndexBuffer(const class std::shared_ptr<class CHazel::IndexBuffer> &)","ph":"X","pid":0,"tid":3967693127,"ts":167749393646},{"cat":"function","dur":101,"name":"__cdecl CHazel::OpenGLTexture2D::OpenGLTexture2D(unsigned int,unsigned int)","ph":"X","pid":0,"tid":3967693127,"ts":167749393768},{"cat":"function","dur":72,"name":"void __cdecl CHazel::OpenGLTexture2D::SetData(void *,unsigned int)","ph":"X","pid":0,"tid":3967693127,"ts":167749393932},{"cat":"function","dur":354,"name":"class std::basic_string<char,struct std::char_traits<char>,class std::allocator<char> > __cdecl CHazel::OpenGLShader::ReadFile(const class std::basic_string<char,struct std::char_traits<char>,class std::allocator<char> > &)","ph":"X","pid":0,"tid":3967693127,"ts":167749394070},{"cat":"function","dur":76,"name":"class std::unordered_map<unsigned int,class std::basic_string<char,struct std::char_traits<char>,class std::allocator<char> >,struct std::hash<unsigned int>,struct std::equal_to<unsigned int>,class std::allocator<struct std::pair<unsigned int const ,class std::basic_string<char,struct std::char_traits<char>,class std::allocator<char> > > > > __cdecl CHazel::OpenGLShader::PreProcess(const class std::basic_string<char,struct std::char_traits<char>,class std::allocator<char> > &)","ph":"X","pid":0,"tid":3967693127,"ts":167749394488},{"cat":"function","dur":18106,"name":"void __cdecl CHazel::OpenGLShader::Compile(const class std::unordered_map<unsigned int,class std::basic_string<char,struct std::char_traits<char>,class std::allocator<char> >,struct std::hash<unsigned int>,struct std::equal_to<unsigned int>,class std::allocator<struct std::pair<unsigned int const ,class std::basic_string<char,struct std::char_traits<char>,class std::allocator<char> > > > > &)","ph":"X","pid":0,"tid":3967693127,"ts":167749394631},{"cat":"function","dur":18815,"name":"__cdecl CHazel::OpenGLShader::OpenGLShader(const class std::basic_string<char,struct std::char_traits<char>,class std::allocator<char> > &)","ph":"X","pid":0,"tid":3967693127,"ts":167749394068},{"cat":"function","dur":29,"name":"void __cdecl CHazel::OpenGLShader::Bind(void) const","ph":"X","pid":0,"tid":3967693127,"ts":167749413022},{"cat":"function","dur":11,"name":"void __cdecl CHazel::OpenGLShader::SetIntArray(const class std::basic_string<char,struct std::char_traits<char>,class std::allocator<char> > &,int *,unsigned int)","ph":"X","pid":0,"tid":3967693127,"ts":167749413101},{"cat":"function","dur":21504,"name":"void __cdecl CHazel::Renderer2D::Init(void)","ph":"X","pid":0,"tid":3967693127,"ts":167749391654},{"cat":"function","dur":21624,"name":"void __cdecl CHazel::Renderer::Init(void)","ph":"X","pid":0,"tid":3967693127,"ts":167749391571},{"cat":"function","dur":338,"name":"void __cdecl CHazel::ImGuiLayer::OnAttach(void)","ph":"X","pid":0,"tid":3967693127,"ts":167749413242},{"cat":"function","dur":401,"name":"void __cdecl CHazel::Application::PushOverlay(class CHazel::Layer *)","ph":"X","pid":0,"tid":3967693127,"ts":167749413236},{"cat":"function","dur":503389,"name":"__cdecl CHazel::Application::Application(void)","ph":"X","pid":0,"tid":3967693127,"ts":167748910286},{"cat":"function","dur":3,"name":"__cdecl CHazel::OrthographicCameca::OrthographicCameca(float,float,float,float)","ph":"X","pid":0,"tid":3967693127,"ts":167749413718},{"cat":"function","dur":331,"name":"stbi_load - OpenGLTexture2D::OpenGLTexture2D(const std:string&)","ph":"X","pid":0,"tid":3967693127,"ts":167749413768},{"cat":"function","dur":5767,"name":"__cdecl CHazel::OpenGLTexture2D::OpenGLTexture2D(const class std::basic_string<char,struct std::char_traits<char>,class std::allocator<char> > &)","ph":"X","pid":0,"tid":3967693127,"ts":167749413768},{"cat":"function","dur":5859,"name":"void __cdecl Sandbox2D::OnAttach(void)","ph":"X","pid":0,"tid":3967693127,"ts":167749413764},{"cat":"function","dur":5903,"name":"void __cdecl CHazel::Application::PushLayer(class CHazel::Layer *)","ph":"X","pid":0,"tid":3967693127,"ts":167749413759}]}